hightime/VERSION
hightime/__init__.py
hightime/_datetime.py
hightime/_timedelta.py
hightime-0.2.0.dist-info/LICENSE
hightime-0.2.0.dist-info/METADATA
hightime-0.2.0.dist-info/WHEEL
hightime-0.2.0.dist-info/top_level.txt
hightime-0.2.0.dist-info/zip-safe
hightime-0.2.0.dist-info/RECORD
